mtproto_mitm/__init__.py
mtproto_mitm/__main__.py
mtproto_mitm/main.py
mtproto_mitm/messages.py
mtproto_mitm/tl/__init__.py
mtproto_mitm/tl/core_types.py
mtproto_mitm/tl/serialization_utils.py
mtproto_mitm/tl/tl_object.py
mtproto_mitm-0.2.2.dist-info/LICENSE
mtproto_mitm-0.2.2.dist-info/METADATA
mtproto_mitm-0.2.2.dist-info/WHEEL
mtproto_mitm-0.2.2.dist-info/RECORD
