Metadata-Version: 2.3
Name: mtproto-mitm
Version: 0.2.2
Summary: Telegram mtproto mitm server.
Author: RuslanUC
Author-email: dev_ruslan_uc@protonmail.com
Requires-Python: >=3.11,<4.0
Classifier: Programming Language :: Python :: 3
Classifier: Programming Language :: Python :: 3.11
Classifier: Programming Language :: Python :: 3.12
Classifier: Programming Language :: Python :: 3.13
Provides-Extra: keys-reload
Requires-Dist: click (>=8.3.1,<9.0.0)
Requires-Dist: mtproto[http,tgcrypto] (>=0.2.1,<0.3.0)
Requires-Dist: pysocks5server (>=0.1.0,<0.2.0)
Requires-Dist: watchfiles (>=1.1.1,<2.0.0) ; extra == "keys-reload"
